scrapybara/__init__.py
scrapybara/anthropic/__init__.py
scrapybara/base_client.py
scrapybara/browser/__init__.py
scrapybara/browser/client.py
scrapybara/client.py
scrapybara/code/__init__.py
scrapybara/code/client.py
scrapybara/core/__init__.py
scrapybara/core/api_error.py
scrapybara/core/client_wrapper.py
scrapybara/core/datetime_utils.py
scrapybara/core/file.py
scrapybara/core/http_client.py
scrapybara/core/jsonable_encoder.py
scrapybara/core/pydantic_utilities.py
scrapybara/core/query_encoder.py
scrapybara/core/remove_none_from_dict.py
scrapybara/core/request_options.py
scrapybara/core/serialization.py
scrapybara/env/__init__.py
scrapybara/env/client.py
scrapybara/environment.py
scrapybara/errors/__init__.py
scrapybara/errors/unprocessable_entity_error.py
scrapybara/herd/__init__.py
scrapybara/instance/__init__.py
scrapybara/instance/client.py
scrapybara/instance/types/__init__.py
scrapybara/instance/types/command.py
scrapybara/instance/types/request.py
scrapybara/notebook/__init__.py
scrapybara/notebook/client.py
scrapybara/openai/__init__.py
scrapybara/prompts/__init__.py
scrapybara/py.typed
scrapybara/tools/__init__.py
scrapybara/types/__init__.py
scrapybara/types/act.py
scrapybara/types/auth_state_response.py
scrapybara/types/bash_response.py
scrapybara/types/browser_authenticate_response.py
scrapybara/types/browser_get_cdp_url_response.py
scrapybara/types/browser_get_current_url_response.py
scrapybara/types/button.py
scrapybara/types/cell_type.py
scrapybara/types/click_mouse_action.py
scrapybara/types/click_mouse_action_click_type.py
scrapybara/types/computer_response.py
scrapybara/types/deployment_config_instance_type.py
scrapybara/types/drag_mouse_action.py
scrapybara/types/edit_response.py
scrapybara/types/env_get_response.py
scrapybara/types/env_response.py
scrapybara/types/execute_cell_request.py
scrapybara/types/file_response.py
scrapybara/types/get_cursor_position_action.py
scrapybara/types/get_instance_response.py
scrapybara-2.5.3.dist-info/METADATA
scrapybara-2.5.3.dist-info/WHEEL
scrapybara-2.5.3.dist-info/RECORD
